streamlit_thesys/__init__.py
streamlit_thesys/demo_data.py
streamlit_thesys/example.py
streamlit_thesys/frontend/build/index.html
streamlit_thesys/frontend/build/assets/KaTeX_AMS-Regular-BQhdFMY1.woff2
streamlit_thesys/frontend/build/assets/KaTeX_AMS-Regular-DMm9YOAa.woff
streamlit_thesys/frontend/build/assets/KaTeX_AMS-Regular-DRggAlZN.ttf
streamlit_thesys/frontend/build/assets/KaTeX_Caligraphic-Bold-ATXxdsX0.ttf
streamlit_thesys/frontend/build/assets/KaTeX_Caligraphic-Bold-BEiXGLvX.woff
streamlit_thesys/frontend/build/assets/KaTeX_Caligraphic-Bold-Dq_IR9rO.woff2
streamlit_thesys/frontend/build/assets/KaTeX_Caligraphic-Regular-CTRA-rTL.woff
streamlit_thesys/frontend/build/assets/KaTeX_Caligraphic-Regular-Di6jR-x-.woff2
streamlit_thesys/frontend/build/assets/KaTeX_Caligraphic-Regular-wX97UBjC.ttf
streamlit_thesys/frontend/build/assets/KaTeX_Fraktur-Bold-BdnERNNW.ttf
streamlit_thesys/frontend/build/assets/KaTeX_Fraktur-Bold-BsDP51OF.woff
streamlit_thesys/frontend/build/assets/KaTeX_Fraktur-Bold-CL6g_b3V.woff2
streamlit_thesys/frontend/build/assets/KaTeX_Fraktur-Regular-CB_wures.ttf
streamlit_thesys/frontend/build/assets/KaTeX_Fraktur-Regular-CTYiF6lA.woff2
streamlit_thesys/frontend/build/assets/KaTeX_Fraktur-Regular-Dxdc4cR9.woff
streamlit_thesys/frontend/build/assets/KaTeX_Main-Bold-Cx986IdX.woff2
streamlit_thesys/frontend/build/assets/KaTeX_Main-Bold-Jm3AIy58.woff
streamlit_thesys/frontend/build/assets/KaTeX_Main-Bold-waoOVXN0.ttf
streamlit_thesys/frontend/build/assets/KaTeX_Main-BoldItalic-DxDJ3AOS.woff2
streamlit_thesys/frontend/build/assets/KaTeX_Main-BoldItalic-DzxPMmG6.ttf
streamlit_thesys/frontend/build/assets/KaTeX_Main-BoldItalic-SpSLRI95.woff
streamlit_thesys/frontend/build/assets/KaTeX_Main-Italic-3WenGoN9.ttf
streamlit_thesys/frontend/build/assets/KaTeX_Main-Italic-BMLOBm91.woff
streamlit_thesys/frontend/build/assets/KaTeX_Main-Italic-NWA7e6Wa.woff2
streamlit_thesys/frontend/build/assets/KaTeX_Main-Regular-B22Nviop.woff2
streamlit_thesys-0.0.2.dist-info/licenses/LICENSE
streamlit_thesys-0.0.2.dist-info/METADATA
streamlit_thesys-0.0.2.dist-info/WHEEL
streamlit_thesys-0.0.2.dist-info/top_level.txt
streamlit_thesys-0.0.2.dist-info/RECORD
