Metadata-Version: 2.4
Name: streamlit-thesys
Version: 0.0.2
Summary: Generative UI for Streamlit powered by C1 by Thesys
Home-page: https://github.com/thesysdev/streamlit-thesys-genui
Author: Thesys
Author-email: engineering@thesys.dev
Keywords: Streamlit,Thesys,C1 by Thesys,Generative UI,LLM UI,AI components,live data visualization,data visualization,agent UI,LLM to UI,streamlit components,generative visualization
Requires-Python: >=3.7
License-File: LICENSE
Requires-Dist: streamlit>=0.63
Requires-Dist: requests>=2.31.0
Requires-Dist: pandas>=1.3.0
Requires-Dist: openpyxl>=3.0.0
Provides-Extra: devel
Requires-Dist: wheel; extra == "devel"
Requires-Dist: pytest==7.4.0; extra == "devel"
Requires-Dist: playwright==1.48.0; extra == "devel"
Requires-Dist: requests==2.31.0; extra == "devel"
Requires-Dist: pytest-playwright-snapshot==1.0; extra == "devel"
Requires-Dist: pytest-rerunfailures==12.0; extra == "devel"
Requires-Dist: openai; extra == "devel"
Dynamic: author
Dynamic: author-email
Dynamic: description
Dynamic: description-content-type
Dynamic: home-page
Dynamic: keywords
Dynamic: license-file
Dynamic: provides-extra
Dynamic: requires-dist
Dynamic: requires-python
Dynamic: summary
